peakshaving_analyzer/PSA.py
peakshaving_analyzer/__init__.py
peakshaving_analyzer/common.py
peakshaving_analyzer/input.py
peakshaving_analyzer/output.py
peakshaving_analyzer/util.py
peakshaving_analyzer-0.1.10.dist-info/licenses/LICENSE
psa_cli/main.py
peakshaving_analyzer-0.1.10.dist-info/METADATA
peakshaving_analyzer-0.1.10.dist-info/WHEEL
peakshaving_analyzer-0.1.10.dist-info/entry_points.txt
peakshaving_analyzer-0.1.10.dist-info/top_level.txt
peakshaving_analyzer-0.1.10.dist-info/RECORD
