Metadata-Version: 2.4
Name: peakshaving-analyzer
Version: 0.1.10
Summary: Peak shaving analysis for industrial load profiles
Author-email: Christoph Komanns <c.komanns@gmail.com>, Florian Maurer <fmaurer@disroot.org>
License-Expression: MIT
Project-URL: Issues, https://github.com/NOWUM/peakshaving_analyzer/issues
Project-URL: Repository, https://github.com/NOWUM/peakshaving-analyzer
Keywords: peak shaving,energy framework,energy optimization,optimization
Classifier: Development Status :: 3 - Alpha
Classifier: Intended Audience :: Developers
Classifier: Operating System :: OS Independent
Classifier: Topic :: Scientific/Engineering
Classifier: Topic :: Software Development :: Libraries :: Python Modules
Classifier: Programming Language :: Python :: 3 :: Only
Classifier: Programming Language :: Python :: 3.10
Classifier: Programming Language :: Python :: 3.11
Classifier: Programming Language :: Python :: 3.12
Classifier: Programming Language :: Python :: 3.13
Requires-Python: >=3.10
License-File: LICENSE
Requires-Dist: numpy>=1.26.4
Requires-Dist: python-dateutil>=2.8.2
Requires-Dist: sqlalchemy>=2.0.9
Requires-Dist: pandas>=2.0.0
Requires-Dist: psycopg2-binary>=2.9.5
Requires-Dist: pyyaml>=6.0
Requires-Dist: pyyaml-include>=2.2a
Requires-Dist: fine>=2.4.1
Requires-Dist: pyomo>=6.8.0
Requires-Dist: pgeocode>=0.5.0
Requires-Dist: highspy
Requires-Dist: gurobipy
Requires-Dist: argcomplete
Provides-Extra: dev
Requires-Dist: ruff>=0.11.5; extra == "dev"
Requires-Dist: build>=1.2.2; extra == "dev"
Requires-Dist: pytest>=8.4.2; extra == "dev"
Dynamic: license-file
